dicio_py/__init__.py
dicio_py/dicio_py.py
dicio_py-2.5.dist-info/LICENSE
dicio_py-2.5.dist-info/METADATA
dicio_py-2.5.dist-info/WHEEL
dicio_py-2.5.dist-info/entry_points.txt
dicio_py-2.5.dist-info/top_level.txt
dicio_py-2.5.dist-info/RECORD
