Metadata-Version: 2.1
Name: dicio-py
Version: 2.5
Summary: Script para buscar o significado de palavras no dicionário online Dicio.
Home-page: https://github.com/Jetrom17/dicio-py
Author: Jeiel Lima Miranda
Classifier: Programming Language :: Python :: 3
Classifier: License :: OSI Approved :: GNU General Public License v3 (GPLv3)
Classifier: Operating System :: OS Independent
Requires-Python: >=3.6
License-File: LICENSE
